load_atoms/__init__.py
load_atoms/atoms_dataset.py
load_atoms/progress.py
load_atoms/utils.py
load_atoms/database/__init__.py
load_atoms/database/backend.py
load_atoms/database/database_entry.py
load_atoms/database/internet.py
load_atoms/database/importers/a_si_24.py
load_atoms/database/importers/ac_2d_22.py
load_atoms/database/importers/ani_1ccx.py
load_atoms/database/importers/ani_1x.py
load_atoms/database/importers/bad_qm9.txt
load_atoms/database/importers/c_gap_17.py
load_atoms/database/importers/c_gap_20u.py
load_atoms/database/importers/c_synth_23m.py
load_atoms/database/importers/go_mace_23.py
load_atoms/database/importers/gst_gap_22.py
load_atoms/database/importers/p_gap_20.py
load_atoms/database/importers/qm7.py
load_atoms/database/importers/qm9.py
load_atoms/database/importers/rmd17.py
load_atoms/database/importers/si_gap_18.py
load_atoms/database/importers/sio2_gap_22.py
load_atoms/database/importers/siox_ace_24.py
load_atoms/scripts/cli.py
load_atoms/visualisation/__init__.py
load_atoms/visualisation/view.js
load_atoms/visualisation/x3d.script
load_atoms-0.3.9.dist-info/LICENSE
load_atoms-0.3.9.dist-info/METADATA
load_atoms-0.3.9.dist-info/WHEEL
load_atoms-0.3.9.dist-info/entry_points.txt
load_atoms-0.3.9.dist-info/top_level.txt
load_atoms-0.3.9.dist-info/RECORD
