Metadata-Version: 2.1
Name: load-atoms
Version: 0.3.9
Summary: Large Open Access Datasets for Atomistic Materials Science (LOAD-AtoMS)
Author-email: John Gardner <gardner.john97@gmail.com>
License: MIT License
Project-URL: Homepage, https://github.com/jla-gardner/load-atoms
Keywords: chemistry,machine learning,datasets
Classifier: License :: OSI Approved :: MIT License
Classifier: Programming Language :: Python
Classifier: Programming Language :: Python :: 3
Requires-Python: >=3.8
License-File: LICENSE
Requires-Dist: ase
Requires-Dist: pyyaml
Requires-Dist: requests
Requires-Dist: numpy
Requires-Dist: pydantic>2.0.0
Requires-Dist: rich
Requires-Dist: ipywidgets
Requires-Dist: lmdb
Requires-Dist: h5py
Provides-Extra: dev
Requires-Dist: notebook; extra == "dev"
Requires-Dist: pytest; extra == "dev"
Requires-Dist: sphinx; extra == "dev"
Requires-Dist: furo; extra == "dev"
Requires-Dist: nbsphinx; extra == "dev"
Requires-Dist: sphinx-autobuild; extra == "dev"
Requires-Dist: pytest-cov; extra == "dev"
Requires-Dist: build; extra == "dev"
Requires-Dist: bumpver; extra == "dev"
Requires-Dist: twine; extra == "dev"
Requires-Dist: ruff; extra == "dev"
Requires-Dist: sphinx-autodoc-typehints; extra == "dev"
Requires-Dist: sphinx-design; extra == "dev"
Requires-Dist: sphinx-copybutton; extra == "dev"
Requires-Dist: sphinx-codeautolink; extra == "dev"
Requires-Dist: sphinxext-opengraph; extra == "dev"
